pumpz/__init__.py
pumpz/masterppl.py
pumpz/pump.py
pumpz/utilities.py
pumpz-0.2.1.dist-info/METADATA
pumpz-0.2.1.dist-info/WHEEL
pumpz-0.2.1.dist-info/licenses/LICENSE
pumpz-0.2.1.dist-info/RECORD
