Metadata-Version: 2.4
Name: pumpz
Version: 0.2.1
Summary: For the automatic creation and sync of .PPL files, used for pump programming
Project-URL: Homepage, https://github.com/Faisal-Shahbaz/pumpz
Author-email: Faisal Shahbaz <faisalsshahbaz1@gmail.com>
License-File: LICENSE
Classifier: License :: OSI Approved :: Mozilla Public License 2.0 (MPL 2.0)
Classifier: Operating System :: OS Independent
Classifier: Programming Language :: Python :: 3.11
Requires-Python: >=3.11
Requires-Dist: sympy>=1.13.3
Requires-Dist: typing>=3.7.4.3
